brawn/__init__.py
brawn/__main__.py
brawn/_cmd.py
brawn/align.py
brawn/alignment.py
brawn/alphabet.py
brawn/constants.py
brawn/distance.py
brawn/path.py
brawn/positions.py
brawn/tree.py
brawn/test/__init__.py
brawn/test/shared.py
brawn/test/test_alignment.py
brawn/test/test_alphabet.py
brawn/test/test_cmd.py
brawn/test/test_full.py
brawn/test/test_positions.py
brawn/test/test_tree.py
brawn-1.0.2.dist-info/LICENSE
brawn-1.0.2.dist-info/METADATA
brawn-1.0.2.dist-info/WHEEL
brawn-1.0.2.dist-info/entry_points.txt
brawn-1.0.2.dist-info/top_level.txt
brawn-1.0.2.dist-info/RECORD
