Metadata-Version: 2.1
Name: brawn
Version: 1.0.2
Summary: A tool for handling repetitive insertions into sequence alignments
Home-page: https://github.com/SJShaw/brawn
Author: Simon Shaw
Author-email: SJShaw@users.noreply.github.com
License: GPLv3+
Classifier: Programming Language :: Python
Classifier: Programming Language :: Python :: 3
Classifier: Development Status :: 3 - Alpha
Classifier: Intended Audience :: Science/Research
Classifier: Topic :: Scientific/Engineering :: Bio-Informatics
Classifier: License :: OSI Approved :: GNU General Public License v3 or later (GPLv3+)
Requires-Python: >=3.9
License-File: LICENSE
Provides-Extra: testing
Requires-Dist: coverage; extra == "testing"
Requires-Dist: mypy==0.982; extra == "testing"
Requires-Dist: pytest<8,>=7.2.0; extra == "testing"
Requires-Dist: pylint>=2.15.2; extra == "testing"
